pydanttention-0.1.2.dist-info/METADATA
pydanttention-0.1.2.dist-info/WHEEL
pydanttention-0.1.2.dist-info/licenses/LICENSE.txt
pydanttention/__init__.py
pydanttention/main.py
pydanttention/models/__init__.py
pydanttention/models/attention/block.py
pydanttention/models/attention/main.py
pydanttention/models/config.py
pydanttention/models/ops/__init__.py
pydanttention/models/ops/base.py
pydanttention/models/ops/main.py
pydanttention/models/ops/simple.py
pydanttention/models/tokens.py
pydanttention/models/transformer.py
pydanttention/original/__init__.py
pydanttention/original/vogel.py
pydanttention/unused.py
pydanttention-0.1.2.dist-info/RECORD
