Metadata-Version: 2.1
Name: pydanttention
Version: 0.1.2
Summary: Transformer model attention in Pydantic.
Keywords: pydantic
Author-Email: Louis Maddox <louismmx@gmail.com>
License: MIT
Classifier: Development Status :: 3 - Alpha
Classifier: Intended Audience :: Developers
Classifier: Natural Language :: English
Classifier: Topic :: Software Development :: Libraries
Classifier: Framework :: Pydantic
Classifier: Framework :: Pydantic :: 2
Classifier: Programming Language :: Python
Classifier: Programming Language :: Python :: 3.10
Classifier: Programming Language :: Python :: 3.11
Project-URL: Homepage, https://github.com/lmmx/pydanttention
Project-URL: Repository, https://github.com/lmmx/pydanttention.git
Requires-Python: >=3.10
Requires-Dist: numpy
Requires-Dist: pydantic>=2.1.1
